cstm/__init__.py
cstm/dataset/__init__.py
cstm/dataset/hospital/__init__.py
cstm/dataset/hospital/sampleData.py
cstm/model/__init__.py
cstm/model/compute.py
cstm/model/visualize.py
cstm/model/stochastic/__init__.py
cstm/model/stochastic/compute.py
cstm/model/stochastic/visualize.py
cstm-0.0.5.dist-info/METADATA
cstm-0.0.5.dist-info/WHEEL
cstm-0.0.5.dist-info/top_level.txt
cstm-0.0.5.dist-info/RECORD
