Metadata-Version: 2.1
Name: cstm
Version: 0.0.5
Summary: Python cstm Package
Home-page: UNKNOWN
Author: Amin Jalali
Author-email: aminjalali@yahoo.com
License: MIT
Platform: UNKNOWN
Requires-Dist: pandas
Requires-Dist: graphviz
